whis/__init__.py
whis/__main__.py
whis/cli.py
whis/config.py
whis/config.template.toml
whis/providers.py
whis/smoke.py
whis/system_prompt.txt
whis/utils.py
whis-0.1.0a5.dist-info/licenses/LICENSE
whis-0.1.0a5.dist-info/METADATA
whis-0.1.0a5.dist-info/WHEEL
whis-0.1.0a5.dist-info/entry_points.txt
whis-0.1.0a5.dist-info/top_level.txt
whis-0.1.0a5.dist-info/RECORD
