Metadata-Version: 2.4
Name: whis
Version: 0.1.0a5
Summary: A tiny Linux command whisperer that suggests shell commands based on natural language.
Author-email: Milan Slesarik <milslesarik@gmail.com>
License: The MIT License (MIT)
Project-URL: Homepage, https://github.com/milano-slesarik/whis
Project-URL: Bug Tracker, https://github.com/milano-slesarik/whis/issues
Classifier: Programming Language :: Python :: 3
Classifier: Programming Language :: Python :: 3.11
Classifier: Programming Language :: Python :: 3.12
Classifier: Programming Language :: Python :: 3.13
Classifier: License :: OSI Approved :: MIT License
Classifier: Operating System :: POSIX :: Linux
Classifier: Environment :: Console
Classifier: Topic :: Utilities
Requires-Python: >=3.10
License-File: LICENSE
Requires-Dist: openai
Requires-Dist: ollama
Requires-Dist: pyperclip
Requires-Dist: tomli>=1.2.0; python_version < "3.11"
Provides-Extra: dev
Requires-Dist: dotenv; extra == "dev"
Requires-Dist: pytest; extra == "dev"
Requires-Dist: pytest-cov; extra == "dev"
Requires-Dist: black; extra == "dev"
Requires-Dist: ruff; extra == "dev"
Requires-Dist: pre-commit<5,>=4.3.0; extra == "dev"
Dynamic: license-file
